itermonkey/__init__.py
itermonkey/dicttools.py
itermonkey/graphtools.py
itermonkey/listtools.py
itermonkey/misctools.py
itermonkey/settools.py
itermonkey/strtools.py
itermonkey-2025.11.3.2.dist-info/licenses/LICENSE
itermonkey-2025.11.3.2.dist-info/METADATA
itermonkey-2025.11.3.2.dist-info/WHEEL
itermonkey-2025.11.3.2.dist-info/top_level.txt
itermonkey-2025.11.3.2.dist-info/RECORD
