Metadata-Version: 2.4
Name: itermonkey
Version: 2025.11.3.2
Summary: A collection of Python utilities for lists, sets, dictionaries, and graphs.
Author-email: aegotastic <pseudopersonal839@gmail.com>
License: MIT
Project-URL: Homepage, https://github.com/aegotastic/IterMonkey
Project-URL: Repository, https://github.com/aegotastic/IterMonkey
Keywords: python,utilities,data structures,algorithms,lists,sets,dictionaries,graphs
Classifier: Programming Language :: Python :: 3
Classifier: License :: OSI Approved :: MIT License
Classifier: Operating System :: OS Independent
Requires-Python: >=3.9
License-File: LICENSE
Requires-Dist: networkx>=3.0
Dynamic: license-file
